flask_cloud_ndb/__init__.py
Flask_Cloud_NDB-0.2.0.dist-info/LICENSE
Flask_Cloud_NDB-0.2.0.dist-info/METADATA
Flask_Cloud_NDB-0.2.0.dist-info/WHEEL
Flask_Cloud_NDB-0.2.0.dist-info/top_level.txt
Flask_Cloud_NDB-0.2.0.dist-info/RECORD
