Metadata-Version: 2.1
Name: Flask-Cloud-NDB
Version: 0.2.0
Summary: Flask Cloud NDB: Adds Google Cloud NDB support to Flask
Home-page: https://github.com/bool-dev/flask-cloud-ndb
Author: Rituraj Dowerah
Author-email: bool.dev@gmail.com
Maintainer: Rituraj Dowerah
Maintainer-email: bool.dev@gmail.com
License: MIT
Project-URL: Documentation, https://github.com/bool-dev/flask-cloud-ndb
Project-URL: Code, https://github.com/bool-dev/flask-cloud-ndb
Project-URL: Issue tracker, https://github.com/bool-dev/flask-cloud-ndb/issues
Platform: any
Classifier: Development Status :: 3 - Alpha
Classifier: Environment :: Web Environment
Classifier: Intended Audience :: Developers
Classifier: License :: OSI Approved :: MIT License
Classifier: Operating System :: OS Independent
Classifier: Programming Language :: Python
Classifier: Programming Language :: Python :: 3
Classifier: Programming Language :: Python :: 3.4
Classifier: Programming Language :: Python :: 3.5
Classifier: Programming Language :: Python :: 3.6
Classifier: Programming Language :: Python :: 3.7
Classifier: Programming Language :: Python :: 3 :: Only
Classifier: Programming Language :: Python :: Implementation :: CPython
Classifier: Programming Language :: Python :: Implementation :: PyPy
Classifier: Topic :: Internet :: WWW/HTTP :: Dynamic Content
Classifier: Topic :: Software Development :: Libraries :: Python Modules
Requires-Python: >= 3.0, != 3.0.*, != 3.1.*, != 3.2.*, != 3.3.*
Requires-Dist: Flask (>=1.1.2)
Requires-Dist: google-cloud-ndb (>=1.2.0)
